{
    "name": "云服务器",
    "host": "117.50.185.11",
    "protocol": "sftp",
    "port": 22,
    "username": "ubuntu",
    "privateKeyPath": "C:\\Users\\weizh\\.ssh\\id_ed25519",
    "remotePath": "/home/ubuntu/Ultralytics-SAM3-WebUI",
    "uploadOnSave": false,
    "useTempFile": false,
    "ignore": [
        "**/.vscode/**",
        "**/.git/**",
        "**/models/**",
        "**/logs/**",
        "**/node_modules/**",
        "**/frontend/node_modules/**",
        "**/frontend/.vite/**",
        "**/frontend/.cache/**",
        "**/.cache/**",
        "**/.pytest_cache/**",
        "**/coverage/**",
        "**/playwright-report/**",
        "**/test-results/**",
        "**/output/**",
        "**/.DS_Store",
        "**/__pycache__/**",
        "**/*.pyc",
        "**/venv/**",
        "**/.env*",
        "**/tmp/**",
        "**/.idea/**",
        "*.log",
        "*.tmp"
    ],
    "watcher": {
        "files": "**/*",
        "autoUpload": true,
        "autoDelete": false
    },
    "syncOption": {
        "skipCreate": false,
        "delete": false,
        "update": true
    }
}
